Metadata-Version: 2.1
Name: iosense-connect-onprem
Version: 0.0.2
Summary: iosense connect library
Author: Faclon-Labs
Author-email: reachus@faclon.com
Classifier: Programming Language :: Python :: 3
Classifier: License :: OSI Approved :: MIT License
Classifier: Operating System :: OS Independent
License-File: LICENSE.txt
